setup.cfg
setup.py
wowapi/__init__.py
wowapi/utility.py
wowapi.egg-info/PKG-INFO
wowapi.egg-info/SOURCES.txt
wowapi.egg-info/dependency_links.txt
wowapi.egg-info/requires.txt
wowapi.egg-info/top_level.txt