Metadata-Version: 1.1
Name: wowapi
Version: 0.4.0
Summary: Python library for the World of Warcraft Community API
Home-page: https://github.com/GoblinLedger/wowapi
Author: Billy Overton
Author-email: billy@billyoverton.com
License: MIT License
Keywords: World of Warcraft
Platform: UNKNOWN
Classifier: Development Status :: 4 - Beta
Classifier: Intended Audience :: Developers
Classifier: License :: OSI Approved :: MIT License
Classifier: Natural Language :: English
Classifier: Topic :: Games/Entertainment
